{"name":"Login failed","id":"login;login-failed","testSteps":[{"number":1,"description":"Example: {email2\u003dJosefergo89@gmail.com, password2\u003dJoselito26267605}","duration":28097,"startTime":"2023-09-28T09:35:36.950262700-05:00[America/Bogota]","screenshots":[{"screenshot":"e234190571427d7bb7d7bb3196d8e75831bbbddbea7cace874aaa72ced02bd50.png","timeStamp":1695911765047}],"result":"SUCCESS","precondition":false,"level":0,"children":[{"number":2,"description":"Given the user enter to the web page","duration":8463,"startTime":"2023-09-28T09:35:36.958262400-05:00[America/Bogota]","screenshots":[{"screenshot":"78d37ae3e38fe0140e18fcdb4d4d0d6b3f8e2c3d03bc5b8390c94d6db50f242a.png","timeStamp":1695911745421}],"result":"SUCCESS","precondition":false,"level":1,"children":[{"number":3,"description":"User opens the https://www.booking.com/","duration":5312,"startTime":"2023-09-28T09:35:36.975262600-05:00[America/Bogota]","result":"SUCCESS","precondition":false,"level":2}]},{"number":4,"description":"And the user clicks on the \u0027iniciar sesion\u0027 button","duration":6821,"startTime":"2023-09-28T09:35:45.423291900-05:00[America/Bogota]","screenshots":[{"screenshot":"78d37ae3e38fe0140e18fcdb4d4d0d6b3f8e2c3d03bc5b8390c94d6db50f242a.png","timeStamp":1695911745425},{"screenshot":"477a447de0df61602b59a97873469284109d07984dd9d6e6c02baf1d171538d8.png","timeStamp":1695911752244}],"result":"SUCCESS","precondition":false,"level":1,"children":[{"number":5,"description":"User click close modal","duration":410,"startTime":"2023-09-28T09:35:45.439296-05:00[America/Bogota]","screenshots":[{"screenshot":"78d37ae3e38fe0140e18fcdb4d4d0d6b3f8e2c3d03bc5b8390c94d6db50f242a.png","timeStamp":1695911745443},{"screenshot":"7e8274db6abc3ee8f5fe5117cc932dd95350bd16966bd8115bb9b6ddb7303eb9.png","timeStamp":1695911745849}],"result":"SUCCESS","precondition":false,"level":2,"children":[{"number":6,"description":"User clicks on close modal","duration":252,"startTime":"2023-09-28T09:35:45.455294600-05:00[America/Bogota]","result":"SUCCESS","precondition":false,"level":3}]},{"number":7,"description":"User click login button","duration":3267,"startTime":"2023-09-28T09:35:45.859982-05:00[America/Bogota]","screenshots":[{"screenshot":"7e8274db6abc3ee8f5fe5117cc932dd95350bd16966bd8115bb9b6ddb7303eb9.png","timeStamp":1695911745861},{"screenshot":"a563266201c42753f6d06aa7cfe52697d62c32ea486b6b0157ac1e8dfcbb612a.png","timeStamp":1695911749126}],"result":"SUCCESS","precondition":false,"level":2,"children":[{"number":8,"description":"User clicks on it is used to sign in to the page","duration":3159,"startTime":"2023-09-28T09:35:45.871985200-05:00[America/Bogota]","result":"SUCCESS","precondition":false,"level":3}]}]},{"number":9,"description":"When the user enter incorrect password\r\n| email2 | password2 |\r\n| Josefergo89@gmail.com | Joselito26267605 |","duration":12629,"startTime":"2023-09-28T09:35:52.246614200-05:00[America/Bogota]","screenshots":[{"screenshot":"477a447de0df61602b59a97873469284109d07984dd9d6e6c02baf1d171538d8.png","timeStamp":1695911752247},{"screenshot":"e234190571427d7bb7d7bb3196d8e75831bbbddbea7cace874aaa72ced02bd50.png","timeStamp":1695911764876}],"result":"SUCCESS","precondition":false,"level":1,"children":[{"number":10,"description":"User login","duration":9106,"startTime":"2023-09-28T09:35:52.261617300-05:00[America/Bogota]","screenshots":[{"screenshot":"477a447de0df61602b59a97873469284109d07984dd9d6e6c02baf1d171538d8.png","timeStamp":1695911752263},{"screenshot":"a24f2481e065117c0d6490b60db2c335ee2a600015f66f3b15403f113aab9245.png","timeStamp":1695911761368}],"result":"SUCCESS","precondition":false,"level":2,"children":[{"number":11,"description":"User enters \u0027Josefergo89@gmail.com\u0027 into it is used to enter the email","duration":376,"startTime":"2023-09-28T09:35:52.276619600-05:00[America/Bogota]","result":"SUCCESS","precondition":false,"level":3},{"number":12,"description":"User clicks on it is used to send the email","duration":151,"startTime":"2023-09-28T09:35:56.666397700-05:00[America/Bogota]","result":"SUCCESS","precondition":false,"level":3},{"number":13,"description":"User enters \u0027Joselito26267605\u0027 into it is used to enter the password","duration":281,"startTime":"2023-09-28T09:35:58.830729400-05:00[America/Bogota]","result":"SUCCESS","precondition":false,"level":3},{"number":14,"description":"User clicks on it is used to log in","duration":154,"startTime":"2023-09-28T09:36:01.132706400-05:00[America/Bogota]","result":"SUCCESS","precondition":false,"level":3}]}]},{"number":15,"description":"Then the user should see the unsuccessful login","duration":167,"startTime":"2023-09-28T09:36:04.878353500-05:00[America/Bogota]","screenshots":[{"screenshot":"e234190571427d7bb7d7bb3196d8e75831bbbddbea7cace874aaa72ced02bd50.png","timeStamp":1695911764880},{"screenshot":"e234190571427d7bb7d7bb3196d8e75831bbbddbea7cace874aaa72ced02bd50.png","timeStamp":1695911765045}],"result":"SUCCESS","precondition":false,"level":1,"children":[{"number":16,"description":"Then validition wrong login should be \u0027\u0026iquest;Eres un robot?\u0027","duration":158,"startTime":"2023-09-28T09:36:04.884353800-05:00[America/Bogota]","screenshots":[{"screenshot":"e234190571427d7bb7d7bb3196d8e75831bbbddbea7cace874aaa72ced02bd50.png","timeStamp":1695911764887},{"screenshot":"e234190571427d7bb7d7bb3196d8e75831bbbddbea7cace874aaa72ced02bd50.png","timeStamp":1695911765042}],"result":"SUCCESS","precondition":false,"level":2}]}]}],"userStory":{"id":"login","storyName":"Login","path":"src/test/resources/features/login.feature","narrative":"  I as user, I need to login","type":"feature"},"featureTag":{"name":"Features/Login","type":"feature","displayName":"Features/Login"},"title":"Login failed","backgroundTitle":"","backgroundDescription":"","tags":[{"name":"Login","type":"feature","displayName":"Login"}],"startTime":"2023-09-28T09:35:36.939256500-05:00[America/Bogota]","duration":28953,"projectKey":"","driver":"chrome","isManualTestingUpToDate":false,"dataTable":{"headers":["email2","password2"],"rows":[{"values":["Josefergo89@gmail.com","Joselito26267605"],"lineNumber":0,"result":"SUCCESS"}],"predefinedRows":true,"scenarioOutline":"And the user clicks on the \u0027iniciar sesion\u0027 button\n\rWhen the user enter incorrect password\n\rThen the user should see the unsuccessful login\n\r","dataSetDescriptors":[{"startRow":0,"rowCount":0,"name":""}]},"manual":false,"testSource":"Cucumber","actors":[{"name":"User","can":["browse the web"]}],"result":"SUCCESS","scenarioOutline":"And the user clicks on the \u0027iniciar sesion\u0027 button\r\nWhen the user enter incorrect password\r\n|email2 | password2|\r\n|\u003cemail2\u003e | \u003cpassword2\u003e|\r\nThen the user should see the unsuccessful login"}